evohome/__init__.py
evohome/auth.py
evohome/const.py
evohome/credentials.py
evohome/exceptions.py
evohome/helpers.py
evohome/py.typed
evohome/time_zone.py
evohome/windows_zones.py
evohome/windows_zones.xml
evohomeasync/__init__.py
evohomeasync/auth.py
evohomeasync/entities.py
evohomeasync/exceptions.py
evohomeasync/main.py
evohomeasync/py.typed
evohomeasync/schemas.py
evohomeasync2/__init__.py
evohomeasync2/auth.py
evohomeasync2/const.py
evohomeasync2/control_system.py
evohomeasync2/exceptions.py
evohomeasync2/gateway.py
evohomeasync2/hotwater.py
evohomeasync2/location.py
evohomeasync2/main.py
evohomeasync2/py.typed
evohomeasync2/zone.py
evohomeasync2/schemas/__init__.py
evohomeasync2/schemas/account.py
evohomeasync2/schemas/config.py
evohomeasync2/schemas/const.py
evohomeasync2/schemas/schedule.py
evohomeasync2/schemas/status.py
evohomeasync2/schemas/typedefs.py
evohome_async-1.0.6.dist-info/METADATA
evohome_async-1.0.6.dist-info/WHEEL
evohome_async-1.0.6.dist-info/entry_points.txt
evohome_async-1.0.6.dist-info/licenses/LICENSE
evohome_async-1.0.6.dist-info/RECORD
