Metadata-Version: 2.4
Name: evohome-async
Version: 1.0.6
Summary: An async client for connecting to Honeywell's TCC RESTful API.
Project-URL: Homepage, https://github.com/zxdavb/evohome-async
Project-URL: Bug Tracker, https://github.com/zxdavb/evohome-async/issues
Project-URL: Wiki, https://github.com/zxdavb/evohome-async/wiki
Author-email: David Bonnes <zxdavb@bonnes.me>
Maintainer-email: David Bonnes <zxdavb@bonnes.me>
License-Expression: Apache-2.0
License-File: LICENSE
Keywords: evohome,honeywell,resideo,round thermostat,tcc,vision pro
Classifier: License :: OSI Approved :: Apache Software License
Classifier: Topic :: Home Automation
Requires-Python: >=3.12
Requires-Dist: aiohttp>=3.11.12
Requires-Dist: aiozoneinfo>=0.2.3
Requires-Dist: voluptuous>=0.15.2
